{
    "natures": [
      { "id": 1, "name": "Hardy", "increased": "none", "decreased": "none" },
      { "id": 2, "name": "Lonely", "increased": "attack", "decreased": "defense" },
      { "id": 3, "name": "Brave", "increased": "attack", "decreased": "speed" },
      { "id": 4, "name": "Adamant", "increased": "attack", "decreased": "special-attack" },
      { "id": 5, "name": "Naughty", "increased": "attack", "decreased": "special-defense" },
      { "id": 6, "name": "Bold", "increased": "defense", "decreased": "attack" },
      { "id": 7, "name": "Docile", "increased": "none", "decreased": "none" },
      { "id": 8, "name": "Relaxed", "increased": "defense", "decreased": "speed" },
      { "id": 9, "name": "Impish", "increased": "defense", "decreased": "special-attack" },
      { "id": 10, "name": "Lax", "increased": "defense", "decreased": "special-defense" },
      { "id": 11, "name": "Timid", "increased": "speed", "decreased": "attack" },
      { "id": 12, "name": "Hasty", "increased": "speed", "decreased": "defense" },
      { "id": 13, "name": "Serious", "increased": "none", "decreased": "none" },
      { "id": 14, "name": "Jolly", "increased": "speed", "decreased": "special-attack" },
      { "id": 15, "name": "Naive", "increased": "speed", "decreased": "special-defense" },
      { "id": 16, "name": "Modest", "increased": "special-attack", "decreased": "attack" },
      { "id": 17, "name": "Mild", "increased": "special-attack", "decreased": "defense" },
      { "id": 18, "name": "Quiet", "increased": "special-attack", "decreased": "speed" },
      { "id": 19, "name": "Bashful", "increased": "none", "decreased": "none" },
      { "id": 20, "name": "Rash", "increased": "special-attack", "decreased": "special-defense" },
      { "id": 21, "name": "Calm", "increased": "special-defense", "decreased": "attack" },
      { "id": 22, "name": "Gentle", "increased": "special-defense", "decreased": "defense" },
      { "id": 23, "name": "Sassy", "increased": "special-defense", "decreased": "speed" },
      { "id": 24, "name": "Careful", "increased": "special-defense", "decreased": "special-attack" },
      { "id": 25, "name": "Quirky", "increased": "none", "decreased": "none" }
    ]
  }